sihm/__init__.py
sihm/__main__.py
sihm/parser.py
sihm/utils.py
sihm/version.py
sihm/template_project/CMakeLists.txt
sihm/template_project/cmake/CMakeGraphVizOptions.cmake
sihm/template_project/dist/html_dependent_on_java.html
sihm/template_project/dist/make_standalone.py
sihm/template_project/src/animator.js
sihm/template_project/src/camera.js
sihm/template_project/src/gui.js
sihm/template_project/utils/fix_glsl_file.py
sihm-0.0.5.dist-info/LICENSE
sihm-0.0.5.dist-info/METADATA
sihm-0.0.5.dist-info/WHEEL
sihm-0.0.5.dist-info/entry_points.txt
sihm-0.0.5.dist-info/top_level.txt
sihm-0.0.5.dist-info/RECORD
