Metadata-Version: 2.1
Name: sihm
Version: 0.0.5
Summary: Standalone Interactive HTML Movie (SIHM).
Home-page: https://github.com/leakec/sihm.git
Author: Carl Leake
Author-email: leakec57@gmail.com
License: MIT
Classifier: Development Status :: 4 - Beta
Classifier: License :: OSI Approved :: MIT License
Classifier: Natural Language :: English
Classifier: Programming Language :: Python :: 3 :: Only
Classifier: Topic :: Scientific/Engineering
Classifier: Topic :: Education
License-File: LICENSE
Requires-Dist: click
Requires-Dist: pyyaml
